cli/__init__.py
cli/tempspace.py
tempspace_cli-1.2.8.dist-info/METADATA
tempspace_cli-1.2.8.dist-info/WHEEL
tempspace_cli-1.2.8.dist-info/entry_points.txt
tempspace_cli-1.2.8.dist-info/top_level.txt
tempspace_cli-1.2.8.dist-info/RECORD
