Metadata-Version: 2.4
Name: tempspace-cli
Version: 1.2.8
Summary: A command-line tool for uploading files to Tempspace.
Author-email: Tempspace <mcbplay1@gmail.com>
License: MIT License
Classifier: Programming Language :: Python :: 3
Classifier: Operating System :: OS Independent
Requires-Python: >=3.8
Requires-Dist: requests==2.32.5
Requires-Dist: requests-toolbelt==1.0.0
Requires-Dist: rich==14.2.0
Requires-Dist: qrcode==8.2
